drf_nested_routing/__init__.py
drf_nested_routing/fields.py
drf_nested_routing/routers.py
drf_nested_routing/serializers.py
drf_nested_routing/views.py
drf_nested_routing-0.10.0.dist-info/LICENSE.md
drf_nested_routing-0.10.0.dist-info/METADATA
drf_nested_routing-0.10.0.dist-info/WHEEL
drf_nested_routing-0.10.0.dist-info/top_level.txt
drf_nested_routing-0.10.0.dist-info/RECORD
